pydm/__init__.py
pydm/parameters_bag.py
pydm/service_container.py
pydmpro-0.1.1.dist-info/licenses/LICENSE
pydmpro-0.1.1.dist-info/METADATA
pydmpro-0.1.1.dist-info/WHEEL
pydmpro-0.1.1.dist-info/top_level.txt
pydmpro-0.1.1.dist-info/RECORD
