Metadata-Version: 2.4
Name: pydmpro
Version: 0.1.1
Summary: Python Dependency Manager
Author-email: Ariana Maghsoudi <ariana.maghsoudi82@gmail.com>
License: MIT
Requires-Python: >=3.8
License-File: LICENSE
Requires-Dist: underpyx>=0.1.1
Provides-Extra: dev
Requires-Dist: pytest; extra == "dev"
Requires-Dist: assertpy; extra == "dev"
Dynamic: license-file
